{"type":"FeatureCollection","metadata":{"name":"Ремонт телефон игровых приставок","creator":"Yandex Map Constructor","description":"мастерская"},"features":[{"type":"Feature","id":0,"geometry":{"type":"Point","coordinates":[37.67079735581956,55.61914489175176]},"properties":{"description":"Россия, Москва, Луганская улица, вл5с4 пав14/1 79197200303","iconCaption":"Ремонт телефон игровых приставок","marker-color":"#1bad03"}}]}